{"name":"Guild House","bg":["tileset","guild"],"size":[24,32],"tiles":[],"elems":[[[6,16],"GuildRug"],[[5,7],"GuildRugSquare"],[[4,12],"GuildPillar"],[[12,12],"GuildPillar"],[[12,4],"GuildPillar"],[[4,4],"GuildPillar"],[[0,8],"GuildPillar"],[[16,8],"GuildPillar"],[[6,3],"GuildBookcase"],[[9,3],"GuildBookcase"],[[2,6],"GuildBookcase"],[[13,6],"GuildBookcase"],[[8,10],"GuildTable"],[[8,6],"GuildCandle"],[[10,7],"GuildCandle"],[[6,7],"GuildCandle"],[[11,10],"GuildCandle"],[[5,10],"GuildCandle"],[[5,19],"GuildCandle"],[[11,19],"GuildCandle"],[[0,11],"GuildPillows"],[[2,9],"GuildPillows"],[[2,11],"GuildPillows"],[[2,15],"GuildPillow"],[[5,15],"GuildPillow"],[[3,16],"GuildPillow"],[[13,14],"GuildBookcase"],[[14,9],"GuildMisc"],[[2,0],"GuildBanner"],[[13,0],"GuildBanner"]],"rooms":[],"edges":[[9,24]]}